arcee/__init__.py
arcee/api.py
arcee/api_handler.py
arcee/api_helpers.py
arcee/config.py
arcee/dalm.py
arcee/py.typed
arcee/cli/__init__.py
arcee/cli/app.py
arcee/cli/errors.py
arcee/cli/typer.py
arcee/cli/commands/__init__.py
arcee/cli/commands/cpt.py
arcee/cli/commands/merging.py
arcee/cli/commands/retriever.py
arcee/cli/commands/sft.py
arcee/cli/handlers/upload.py
arcee/cli/handlers/weights.py
arcee/schemas/__init__.py
arcee/schemas/doc.py
arcee/schemas/routes.py
arcee_py-2.0.1.dist-info/METADATA
arcee_py-2.0.1.dist-info/WHEEL
arcee_py-2.0.1.dist-info/entry_points.txt
arcee_py-2.0.1.dist-info/RECORD
