Metadata-Version: 2.3
Name: arcee-py
Version: 2.0.1
Dynamic: Summary
Project-URL: Home, https://arcee.ai
Author-email: Jacob Solowetz <jacob@arcee.ai>, Ben Epstein <ben@arcee.ai>
License: MIT
Requires-Python: >=3.8
Requires-Dist: datasets<3.0,>=2.19.2
Requires-Dist: pydantic<3.0,>=2.4.2
Requires-Dist: pyyaml<7.0,>=6.0.1
Requires-Dist: requests<3.0,>=2.32.2
Requires-Dist: rich<14.0,>=13.7.1
Requires-Dist: strenum<1.0,>=0.4.15
Requires-Dist: typer<1.0,>=0.12.3
Provides-Extra: cli
Requires-Dist: pandas; extra == 'cli'
Provides-Extra: dev
Requires-Dist: black; extra == 'dev'
Requires-Dist: invoke; extra == 'dev'
Requires-Dist: mypy; extra == 'dev'
Requires-Dist: pandas; extra == 'dev'
Requires-Dist: pandas-stubs; extra == 'dev'
Requires-Dist: pdoc3; (python_version >= '3.8') and extra == 'dev'
Requires-Dist: pytest; extra == 'dev'
Requires-Dist: pytest-cov; extra == 'dev'
Requires-Dist: pytest-env; extra == 'dev'
Requires-Dist: ruff; extra == 'dev'
Requires-Dist: types-pyyaml; extra == 'dev'
Requires-Dist: types-requests; extra == 'dev'
